pygess/__init__.py
pygess/data.py
pygess/entity.py
pygess/physics.py
pygess/utilities.py
pygess_py-3.0.26.dist-info/METADATA
pygess_py-3.0.26.dist-info/WHEEL
pygess_py-3.0.26.dist-info/RECORD
