Metadata-Version: 2.1
Name: pygess-py
Version: 3.0.26
Summary: Pygame Essentials
License: MIT
Author: Abhijay Bidari
Author-email: craftyryte2011@gmail.com
Requires-Python: >=3.12,<4.0
Classifier: License :: OSI Approved :: MIT License
Classifier: Programming Language :: Python :: 3
Classifier: Programming Language :: Python :: 3.12
Requires-Dist: pygame-ce (>=2.5.1,<3.0.0)
Requires-Dist: uuid (>=1.30,<2.0)
